HTSeqCountCluster/__init__.py
HTSeqCountCluster/htseq_count_cluster.py
HTSeqCountCluster/mergecounts.py
HTSeqCountCluster/logger/__init__.py
HTSeqCountCluster/logger/logger.py
HTSeqCountCluster/pbsjob/__init__.py
HTSeqCountCluster/pbsjob/pbsconfig.py
HTSeqCountCluster/pbsjob/pbsjob.py
HTSeqCountCluster/pbsjob/pbsutils.py
HTSeqCountCluster/pbsjob/qstat.py
HTSeqCountCluster/pbsjob/temp.pbs
HTSeqCountCluster/utils/__init__.py
htseqcountcluster-1.5.dist-info/licenses/LICENSE
tests/__init__.py
tests/test_htseq_count_cluster.py
tests/test_mergecounts.py
tests/test_utils.py
tests/data/__init__.py
htseqcountcluster-1.5.dist-info/METADATA
htseqcountcluster-1.5.dist-info/WHEEL
htseqcountcluster-1.5.dist-info/entry_points.txt
htseqcountcluster-1.5.dist-info/top_level.txt
htseqcountcluster-1.5.dist-info/RECORD
