Metadata-Version: 2.4
Name: HTSeqCountCluster
Version: 1.5
Summary: A cli for running multiple pbs/qsub jobs with HTSeq's htseq-count script on a cluster.
Home-page: https://github.com/datasnakes/htseq-count-cluster
Author: Shaurita Hutchins & Robert Gilmore
Author-email: Shaurita Hutchins & Robert Gilmore <datasnakes@gmail.com>
License: MIT
Project-URL: Homepage, https://github.com/datasnakes/htseq-count-cluster
Project-URL: Documentation, https://tinyurl.com/yb7kz7zz
Project-URL: Website, https://tinyurl.com/yb7kz7zz
Keywords: science,lab,pyschiatry,rnaseq,htseq
Classifier: Development Status :: 5 - Production/Stable
Classifier: Natural Language :: English
Classifier: Programming Language :: Python :: 3
Classifier: Programming Language :: Python :: 3.9
Classifier: Programming Language :: Python :: 3.10
Classifier: Programming Language :: Python :: 3.11
Classifier: Programming Language :: Python :: 3.12
Classifier: License :: OSI Approved :: MIT License
Requires-Python: >=3.9
License-File: LICENSE
Requires-Dist: HTSeq>=0.9.1
Requires-Dist: pandas>=0.20.3
Requires-Dist: logzero>=1.3.1
Provides-Extra: test
Requires-Dist: pytest>=6.0; extra == "test"
Requires-Dist: pytest-cov; extra == "test"
Provides-Extra: dev
Requires-Dist: pytest>=6.0; extra == "dev"
Requires-Dist: pytest-cov; extra == "dev"
Requires-Dist: sphinx; extra == "dev"
Requires-Dist: myst-parser; extra == "dev"
Dynamic: author
Dynamic: home-page
Dynamic: license-file
Dynamic: requires-python
